MutagenesisForge/__init__.py
MutagenesisForge/context.py
MutagenesisForge/exhaustive.py
MutagenesisForge/main.py
MutagenesisForge/mutation_model.py
MutagenesisForge/test.ipynb
mutagenesisforge-1.0.1.dist-info/LICENSE
mutagenesisforge-1.0.1.dist-info/METADATA
mutagenesisforge-1.0.1.dist-info/WHEEL
mutagenesisforge-1.0.1.dist-info/entry_points.txt
mutagenesisforge-1.0.1.dist-info/RECORD
